{"years":[{"date":"1997","value":"25142","label":"1997","year":"1997","month":"","quarter":"","sourceDataset":"PUSF","updateDate":"2015-10-20T23:00:00.000Z"},{"date":"1998","value":"27570","label":"1998","year":"1998","month":"","quarter":"","sourceDataset":"PUSF","updateDate":"2015-10-20T23:00:00.000Z"},{"date":"1999","value":"30493","label":"1999","year":"1999","month":"","quarter":"","sourceDataset":"PUSF","updateDate":"2015-10-20T23:00:00.000Z"},{"date":"2000","value":"33496","label":"2000","year":"2000","month":"","quarter":"","sourceDataset":"PUSF","updateDate":"2015-10-20T23:00:00.000Z"},{"date":"2001","value":"37731","label":"2001","year":"2001","month":"","quarter":"","sourceDataset":"PUSF","updateDate":"2015-10-20T23:00:00.000Z"},{"date":"2002","value":"42205","label":"2002","year":"2002","month":"","quarter":"","sourceDataset":"PUSF","updateDate":"2015-10-20T23:00:00.000Z"},{"date":"2003","value":"47613","label":"2003","year":"2003","month":"","quarter":"","sourceDataset":"PUSF","updateDate":"2015-10-20T23:00:00.000Z"},{"date":"2004","value":"52277","label":"2004","year":"2004","month":"","quarter":"","sourceDataset":"PUSF","updateDate":"2015-10-20T23:00:00.000Z"},{"date":"2005","value":"55751","label":"2005","year":"2005","month":"","quarter":"","sourceDataset":"PUSF","updateDate":"2015-10-20T23:00:00.000Z"},{"date":"2006","value":"61467","label":"2006","year":"2006","month":"","quarter":"","sourceDataset":"PUSF","updateDate":"2015-10-20T23:00:00.000Z"},{"date":"2007","value":"64486","label":"2007","year":"2007","month":"","quarter":"","sourceDataset":"PUSF","updateDate":"2016-06-21T08:30:00.000Z"},{"date":"2008","value":"68836","label":"2008","year":"2008","month":"","quarter":"","sourceDataset":"PUSF","updateDate":"2016-06-21T08:30:00.000Z"},{"date":"2009","value":"72903","label":"2009","year":"2009","month":"","quarter":"","sourceDataset":"PUSF","updateDate":"2016-06-21T08:30:00.000Z"},{"date":"2010","value":"72208","label":"2010","year":"2010","month":"","quarter":"","sourceDataset":"PUSF","updateDate":"2016-06-21T08:30:00.000Z"},{"date":"2011","value":"70508","label":"2011","year":"2011","month":"","quarter":"","sourceDataset":"PUSF","updateDate":"2016-06-21T08:30:00.000Z"},{"date":"2012","value":"69943","label":"2012","year":"2012","month":"","quarter":"","sourceDataset":"PUSF","updateDate":"2016-06-21T08:30:00.000Z"},{"date":"2013","value":"72451","label":"2013","year":"2013","month":"","quarter":"","sourceDataset":"PUSF","updateDate":"2016-06-21T08:30:00.000Z"},{"date":"2014","value":"74392","label":"2014","year":"2014","month":"","quarter":"","sourceDataset":"PUSF","updateDate":"2016-10-20T23:00:00.000Z"},{"date":"2015","value":"75299","label":"2015","year":"2015","month":"","quarter":"","sourceDataset":"PUSF","updateDate":"2016-12-21T00:00:00.000Z"}],"quarters":[{"date":"1997 Q1","value":"5931","label":"1997 Q1","year":"1997","month":"","quarter":"Q1","sourceDataset":"PUSF","updateDate":"2015-10-20T23:00:00.000Z"},{"date":"1997 Q2","value":"6424","label":"1997 Q2","year":"1997","month":"","quarter":"Q2","sourceDataset":"PUSF","updateDate":"2015-10-20T23:00:00.000Z"},{"date":"1997 Q3","value":"6403","label":"1997 Q3","year":"1997","month":"","quarter":"Q3","sourceDataset":"PUSF","updateDate":"2015-10-20T23:00:00.000Z"},{"date":"1997 Q4","value":"6384","label":"1997 Q4","year":"1997","month":"","quarter":"Q4","sourceDataset":"PUSF","updateDate":"2015-10-20T23:00:00.000Z"},{"date":"1998 Q1","value":"6387","label":"1998 Q1","year":"1998","month":"","quarter":"Q1","sourceDataset":"PUSF","updateDate":"2015-10-20T23:00:00.000Z"},{"date":"1998 Q2","value":"7073","label":"1998 Q2","year":"1998","month":"","quarter":"Q2","sourceDataset":"PUSF","updateDate":"2015-10-20T23:00:00.000Z"},{"date":"1998 Q3","value":"7057","label":"1998 Q3","year":"1998","month":"","quarter":"Q3","sourceDataset":"PUSF","updateDate":"2015-10-20T23:00:00.000Z"},{"date":"1998 Q4","value":"7053","label":"1998 Q4","year":"1998","month":"","quarter":"Q4","sourceDataset":"PUSF","updateDate":"2015-10-20T23:00:00.000Z"},{"date":"1999 Q1","value":"7047","label":"1999 Q1","year":"1999","month":"","quarter":"Q1","sourceDataset":"PUSF","updateDate":"2015-10-20T23:00:00.000Z"},{"date":"1999 Q2","value":"7835","label":"1999 Q2","year":"1999","month":"","quarter":"Q2","sourceDataset":"PUSF","updateDate":"2015-10-20T23:00:00.000Z"},{"date":"1999 Q3","value":"7795","label":"1999 Q3","year":"1999","month":"","quarter":"Q3","sourceDataset":"PUSF","updateDate":"2015-10-20T23:00:00.000Z"},{"date":"1999 Q4","value":"7816","label":"1999 Q4","year":"1999","month":"","quarter":"Q4","sourceDataset":"PUSF","updateDate":"2015-10-20T23:00:00.000Z"},{"date":"2000 Q1","value":"7801","label":"2000 Q1","year":"2000","month":"","quarter":"Q1","sourceDataset":"PUSF","updateDate":"2015-10-20T23:00:00.000Z"},{"date":"2000 Q2","value":"8593","label":"2000 Q2","year":"2000","month":"","quarter":"Q2","sourceDataset":"PUSF","updateDate":"2015-10-20T23:00:00.000Z"},{"date":"2000 Q3","value":"8568","label":"2000 Q3","year":"2000","month":"","quarter":"Q3","sourceDataset":"PUSF","updateDate":"2015-10-20T23:00:00.000Z"},{"date":"2000 Q4","value":"8534","label":"2000 Q4","year":"2000","month":"","quarter":"Q4","sourceDataset":"PUSF","updateDate":"2015-10-20T23:00:00.000Z"},{"date":"2001 Q1","value":"8541","label":"2001 Q1","year":"2001","month":"","quarter":"Q1","sourceDataset":"PUSF","updateDate":"2015-10-20T23:00:00.000Z"},{"date":"2001 Q2","value":"9761","label":"2001 Q2","year":"2001","month":"","quarter":"Q2","sourceDataset":"PUSF","updateDate":"2015-10-20T23:00:00.000Z"},{"date":"2001 Q3","value":"9739","label":"2001 Q3","year":"2001","month":"","quarter":"Q3","sourceDataset":"PUSF","updateDate":"2015-10-20T23:00:00.000Z"},{"date":"2001 Q4","value":"9690","label":"2001 Q4","year":"2001","month":"","quarter":"Q4","sourceDataset":"PUSF","updateDate":"2015-10-20T23:00:00.000Z"},{"date":"2002 Q1","value":"9686","label":"2002 Q1","year":"2002","month":"","quarter":"Q1","sourceDataset":"PUSF","updateDate":"2015-10-20T23:00:00.000Z"},{"date":"2002 Q2","value":"10839","label":"2002 Q2","year":"2002","month":"","quarter":"Q2","sourceDataset":"PUSF","updateDate":"2015-10-20T23:00:00.000Z"},{"date":"2002 Q3","value":"10839","label":"2002 Q3","year":"2002","month":"","quarter":"Q3","sourceDataset":"PUSF","updateDate":"2015-10-20T23:00:00.000Z"},{"date":"2002 Q4","value":"10841","label":"2002 Q4","year":"2002","month":"","quarter":"Q4","sourceDataset":"PUSF","updateDate":"2015-10-20T23:00:00.000Z"},{"date":"2003 Q1","value":"10843","label":"2003 Q1","year":"2003","month":"","quarter":"Q1","sourceDataset":"PUSF","updateDate":"2015-10-20T23:00:00.000Z"},{"date":"2003 Q2","value":"12327","label":"2003 Q2","year":"2003","month":"","quarter":"Q2","sourceDataset":"PUSF","updateDate":"2015-10-20T23:00:00.000Z"},{"date":"2003 Q3","value":"12228","label":"2003 Q3","year":"2003","month":"","quarter":"Q3","sourceDataset":"PUSF","updateDate":"2015-10-20T23:00:00.000Z"},{"date":"2003 Q4","value":"12215","label":"2003 Q4","year":"2003","month":"","quarter":"Q4","sourceDataset":"PUSF","updateDate":"2015-10-20T23:00:00.000Z"},{"date":"2004 Q1","value":"12123","label":"2004 Q1","year":"2004","month":"","quarter":"Q1","sourceDataset":"PUSF","updateDate":"2015-10-20T23:00:00.000Z"},{"date":"2004 Q2","value":"13419","label":"2004 Q2","year":"2004","month":"","quarter":"Q2","sourceDataset":"PUSF","updateDate":"2015-10-20T23:00:00.000Z"},{"date":"2004 Q3","value":"13387","label":"2004 Q3","year":"2004","month":"","quarter":"Q3","sourceDataset":"PUSF","updateDate":"2015-10-20T23:00:00.000Z"},{"date":"2004 Q4","value":"13348","label":"2004 Q4","year":"2004","month":"","quarter":"Q4","sourceDataset":"PUSF","updateDate":"2015-10-20T23:00:00.000Z"},{"date":"2005 Q1","value":"13289","label":"2005 Q1","year":"2005","month":"","quarter":"Q1","sourceDataset":"PUSF","updateDate":"2015-10-20T23:00:00.000Z"},{"date":"2005 Q2","value":"14191","label":"2005 Q2","year":"2005","month":"","quarter":"Q2","sourceDataset":"PUSF","updateDate":"2015-10-20T23:00:00.000Z"},{"date":"2005 Q3","value":"14148","label":"2005 Q3","year":"2005","month":"","quarter":"Q3","sourceDataset":"PUSF","updateDate":"2015-10-20T23:00:00.000Z"},{"date":"2005 Q4","value":"14123","label":"2005 Q4","year":"2005","month":"","quarter":"Q4","sourceDataset":"PUSF","updateDate":"2015-10-20T23:00:00.000Z"},{"date":"2006 Q1","value":"14673","label":"2006 Q1","year":"2006","month":"","quarter":"Q1","sourceDataset":"PUSF","updateDate":"2015-10-20T23:00:00.000Z"},{"date":"2006 Q2","value":"15637","label":"2006 Q2","year":"2006","month":"","quarter":"Q2","sourceDataset":"PUSF","updateDate":"2015-10-20T23:00:00.000Z"},{"date":"2006 Q3","value":"15594","label":"2006 Q3","year":"2006","month":"","quarter":"Q3","sourceDataset":"PUSF","updateDate":"2015-10-20T23:00:00.000Z"},{"date":"2006 Q4","value":"15563","label":"2006 Q4","year":"2006","month":"","quarter":"Q4","sourceDataset":"PUSF","updateDate":"2015-10-20T23:00:00.000Z"},{"date":"2007 Q1","value":"15542","label":"2007 Q1","year":"2007","month":"","quarter":"Q1","sourceDataset":"PUSF","updateDate":"2015-10-20T23:00:00.000Z"},{"date":"2007 Q2","value":"16324","label":"2007 Q2","year":"2007","month":"","quarter":"Q2","sourceDataset":"PUSF","updateDate":"2016-06-21T08:30:00.000Z"},{"date":"2007 Q3","value":"16238","label":"2007 Q3","year":"2007","month":"","quarter":"Q3","sourceDataset":"PUSF","updateDate":"2015-10-20T23:00:00.000Z"},{"date":"2007 Q4","value":"16382","label":"2007 Q4","year":"2007","month":"","quarter":"Q4","sourceDataset":"PUSF","updateDate":"2016-06-21T08:30:00.000Z"},{"date":"2008 Q1","value":"16296","label":"2008 Q1","year":"2008","month":"","quarter":"Q1","sourceDataset":"PUSF","updateDate":"2016-06-21T08:30:00.000Z"},{"date":"2008 Q2","value":"17138","label":"2008 Q2","year":"2008","month":"","quarter":"Q2","sourceDataset":"PUSF","updateDate":"2016-06-21T08:30:00.000Z"},{"date":"2008 Q3","value":"17492","label":"2008 Q3","year":"2008","month":"","quarter":"Q3","sourceDataset":"PUSF","updateDate":"2016-06-21T08:30:00.000Z"},{"date":"2008 Q4","value":"17910","label":"2008 Q4","year":"2008","month":"","quarter":"Q4","sourceDataset":"PUSF","updateDate":"2016-06-21T08:30:00.000Z"},{"date":"2009 Q1","value":"18032","label":"2009 Q1","year":"2009","month":"","quarter":"Q1","sourceDataset":"PUSF","updateDate":"2016-06-21T08:30:00.000Z"},{"date":"2009 Q2","value":"18146","label":"2009 Q2","year":"2009","month":"","quarter":"Q2","sourceDataset":"PUSF","updateDate":"2016-06-21T08:30:00.000Z"},{"date":"2009 Q3","value":"18282","label":"2009 Q3","year":"2009","month":"","quarter":"Q3","sourceDataset":"PUSF","updateDate":"2016-06-21T08:30:00.000Z"},{"date":"2009 Q4","value":"18443","label":"2009 Q4","year":"2009","month":"","quarter":"Q4","sourceDataset":"PUSF","updateDate":"2016-06-21T08:30:00.000Z"},{"date":"2010 Q1","value":"18511","label":"2010 Q1","year":"2010","month":"","quarter":"Q1","sourceDataset":"PUSF","updateDate":"2016-06-21T08:30:00.000Z"},{"date":"2010 Q2","value":"17979","label":"2010 Q2","year":"2010","month":"","quarter":"Q2","sourceDataset":"PUSF","updateDate":"2016-06-21T08:30:00.000Z"},{"date":"2010 Q3","value":"17646","label":"2010 Q3","year":"2010","month":"","quarter":"Q3","sourceDataset":"PUSF","updateDate":"2016-06-21T08:30:00.000Z"},{"date":"2010 Q4","value":"18072","label":"2010 Q4","year":"2010","month":"","quarter":"Q4","sourceDataset":"PUSF","updateDate":"2016-06-21T08:30:00.000Z"},{"date":"2011 Q1","value":"18502","label":"2011 Q1","year":"2011","month":"","quarter":"Q1","sourceDataset":"PUSF","updateDate":"2016-06-21T08:30:00.000Z"},{"date":"2011 Q2","value":"17326","label":"2011 Q2","year":"2011","month":"","quarter":"Q2","sourceDataset":"PUSF","updateDate":"2016-06-21T08:30:00.000Z"},{"date":"2011 Q3","value":"17292","label":"2011 Q3","year":"2011","month":"","quarter":"Q3","sourceDataset":"PUSF","updateDate":"2015-10-20T23:00:00.000Z"},{"date":"2011 Q4","value":"17388","label":"2011 Q4","year":"2011","month":"","quarter":"Q4","sourceDataset":"PUSF","updateDate":"2015-10-20T23:00:00.000Z"},{"date":"2012 Q1","value":"17485","label":"2012 Q1","year":"2012","month":"","quarter":"Q1","sourceDataset":"PUSF","updateDate":"2016-06-21T08:30:00.000Z"},{"date":"2012 Q2","value":"17512","label":"2012 Q2","year":"2012","month":"","quarter":"Q2","sourceDataset":"PUSF","updateDate":"2016-06-21T08:30:00.000Z"},{"date":"2012 Q3","value":"17426","label":"2012 Q3","year":"2012","month":"","quarter":"Q3","sourceDataset":"PUSF","updateDate":"2016-06-21T08:30:00.000Z"},{"date":"2012 Q4","value":"17520","label":"2012 Q4","year":"2012","month":"","quarter":"Q4","sourceDataset":"PUSF","updateDate":"2016-06-21T08:30:00.000Z"},{"date":"2013 Q1","value":"17469","label":"2013 Q1","year":"2013","month":"","quarter":"Q1","sourceDataset":"PUSF","updateDate":"2016-06-21T08:30:00.000Z"},{"date":"2013 Q2","value":"18375","label":"2013 Q2","year":"2013","month":"","quarter":"Q2","sourceDataset":"PUSF","updateDate":"2016-06-21T08:30:00.000Z"},{"date":"2013 Q3","value":"18262","label":"2013 Q3","year":"2013","month":"","quarter":"Q3","sourceDataset":"PUSF","updateDate":"2016-06-21T08:30:00.000Z"},{"date":"2013 Q4","value":"18345","label":"2013 Q4","year":"2013","month":"","quarter":"Q4","sourceDataset":"PUSF","updateDate":"2016-06-21T08:30:00.000Z"},{"date":"2014 Q1","value":"18281","label":"2014 Q1","year":"2014","month":"","quarter":"Q1","sourceDataset":"PUSF","updateDate":"2016-06-21T08:30:00.000Z"},{"date":"2014 Q2","value":"18734","label":"2014 Q2","year":"2014","month":"","quarter":"Q2","sourceDataset":"PUSF","updateDate":"2016-10-20T23:00:00.000Z"},{"date":"2014 Q3","value":"18630","label":"2014 Q3","year":"2014","month":"","quarter":"Q3","sourceDataset":"PUSF","updateDate":"2016-10-20T23:00:00.000Z"},{"date":"2014 Q4","value":"18747","label":"2014 Q4","year":"2014","month":"","quarter":"Q4","sourceDataset":"PUSF","updateDate":"2016-10-20T23:00:00.000Z"},{"date":"2015 Q1","value":"18720","label":"2015 Q1","year":"2015","month":"","quarter":"Q1","sourceDataset":"PUSF","updateDate":"2016-12-21T00:00:00.000Z"},{"date":"2015 Q2","value":"18920","label":"2015 Q2","year":"2015","month":"","quarter":"Q2","sourceDataset":"PUSF","updateDate":"2016-12-21T00:00:00.000Z"},{"date":"2015 Q3","value":"18857","label":"2015 Q3","year":"2015","month":"","quarter":"Q3","sourceDataset":"PUSF","updateDate":"2016-12-21T00:00:00.000Z"},{"date":"2015 Q4","value":"18802","label":"2015 Q4","year":"2015","month":"","quarter":"Q4","sourceDataset":"PUSF","updateDate":"2016-12-21T00:00:00.000Z"},{"date":"2016 Q1","value":"18791","label":"2016 Q1","year":"2016","month":"","quarter":"Q1","sourceDataset":"PUSF","updateDate":"2016-12-21T00:00:00.000Z"},{"date":"2016 Q2","value":"19068","label":"2016 Q2","year":"2016","month":"","quarter":"Q2","sourceDataset":"PUSF","updateDate":"2016-12-21T00:00:00.000Z"},{"date":"2016 Q3","value":"19008","label":"2016 Q3","year":"2016","month":"","quarter":"Q3","sourceDataset":"PUSF","updateDate":"2016-12-21T00:00:00.000Z"}],"months":[],"sourceDatasets":[],"relatedDatasets":[{"uri":"/economy/governmentpublicsectorandtaxes/publicsectorfinance/datasets/publicsectorfinances"}],"relatedDocuments":[{"uri":"/economy/governmentpublicsectorandtaxes/publicsectorfinance/bulletins/publicsectorfinances/latest"}],"versions":[{"uri":"/economy/governmentpublicsectorandtaxes/publicsectorfinance/timeseries/mse9/pusf/previous/v1","updateDate":"2015-12-22T00:00:00.000Z","correctionNotice":"","label":"v1"},{"uri":"/economy/governmentpublicsectorandtaxes/publicsectorfinance/timeseries/mse9/pusf/previous/v2","updateDate":"2015-12-22T00:00:00.000Z","correctionNotice":"","label":"v2"},{"uri":"/economy/governmentpublicsectorandtaxes/publicsectorfinance/timeseries/mse9/pusf/previous/v3","updateDate":"2016-03-22T09:30:00.000Z","correctionNotice":"","label":"v3"},{"uri":"/economy/governmentpublicsectorandtaxes/publicsectorfinance/timeseries/mse9/pusf/previous/v4","updateDate":"2016-04-21T08:30:00.000Z","correctionNotice":"","label":"v4"},{"uri":"/economy/governmentpublicsectorandtaxes/publicsectorfinance/timeseries/mse9/pusf/previous/v5","updateDate":"2016-06-21T08:30:00.000Z","correctionNotice":"","label":"v5"},{"uri":"/economy/governmentpublicsectorandtaxes/publicsectorfinance/timeseries/mse9/pusf/previous/v6","updateDate":"2016-07-21T08:30:00.000Z","correctionNotice":"","label":"v6"},{"uri":"/economy/governmentpublicsectorandtaxes/publicsectorfinance/timeseries/mse9/pusf/previous/v7","updateDate":"2016-09-21T08:30:00.000Z","correctionNotice":"","label":"v7"},{"uri":"/economy/governmentpublicsectorandtaxes/publicsectorfinance/timeseries/mse9/pusf/previous/v8","updateDate":"2016-10-21T08:30:00.000Z","correctionNotice":"","label":"v8"},{"uri":"/economy/governmentpublicsectorandtaxes/publicsectorfinance/timeseries/mse9/pusf/previous/v9","updateDate":"2016-12-21T09:30:00.000Z","correctionNotice":"","label":"v9"}],"type":"timeseries","uri":"/economy/governmentpublicsectorandtaxes/publicsectorfinance/timeseries/mse9/pusf","description":{"title":"LG: Current expenditure: Purchase of goods and services: £m CPNSA       ","contact":{"email":"fraser.munro@ons.gsi.gov.uk","name":"Fraser Munro","telephone":"+44 (0)1633 456402"},"releaseDate":"2016-12-21T00:00:00.000Z","nextRelease":"24 January 2017","datasetId":"PUSF","datasetUri":"/economy/governmentpublicsectorandtaxes/publicsectorfinance/datasets/publicsectorfinances","cdid":"MSE9","unit":"m","preUnit":"£","source":"","date":"2016 Q3","number":"19008","sampleSize":"0"}}