{"years":[{"date":"1948","value":"34662","label":"1948","year":"1948","month":"","quarter":"","sourceDataset":"UKEA","updateDate":"2016-06-30T08:30:00.000Z"},{"date":"1949","value":"37383","label":"1949","year":"1949","month":"","quarter":"","sourceDataset":"UKEA","updateDate":"2016-06-30T08:30:00.000Z"},{"date":"1950","value":"37705","label":"1950","year":"1950","month":"","quarter":"","sourceDataset":"UKEA","updateDate":"2016-06-30T08:30:00.000Z"},{"date":"1951","value":"40353","label":"1951","year":"1951","month":"","quarter":"","sourceDataset":"UKEA","updateDate":"2016-06-30T08:30:00.000Z"},{"date":"1952","value":"37360","label":"1952","year":"1952","month":"","quarter":"","sourceDataset":"UKEA","updateDate":"2016-06-30T08:30:00.000Z"},{"date":"1953","value":"40309","label":"1953","year":"1953","month":"","quarter":"","sourceDataset":"UKEA","updateDate":"2016-06-30T08:30:00.000Z"},{"date":"1954","value":"41784","label":"1954","year":"1954","month":"","quarter":"","sourceDataset":"UKEA","updateDate":"2016-06-30T08:30:00.000Z"},{"date":"1955","value":"45924","label":"1955","year":"1955","month":"","quarter":"","sourceDataset":"UKEA","updateDate":"2016-06-30T08:30:00.000Z"},{"date":"1956","value":"46089","label":"1956","year":"1956","month":"","quarter":"","sourceDataset":"UKEA","updateDate":"2016-06-30T08:30:00.000Z"},{"date":"1957","value":"47262","label":"1957","year":"1957","month":"","quarter":"","sourceDataset":"UKEA","updateDate":"2016-06-30T08:30:00.000Z"},{"date":"1958","value":"47801","label":"1958","year":"1958","month":"","quarter":"","sourceDataset":"UKEA","updateDate":"2016-06-30T08:30:00.000Z"},{"date":"1959","value":"50974","label":"1959","year":"1959","month":"","quarter":"","sourceDataset":"UKEA","updateDate":"2016-06-30T08:30:00.000Z"},{"date":"1960","value":"57103","label":"1960","year":"1960","month":"","quarter":"","sourceDataset":"UKEA","updateDate":"2016-06-30T08:30:00.000Z"},{"date":"1961","value":"56709","label":"1961","year":"1961","month":"","quarter":"","sourceDataset":"UKEA","updateDate":"2016-06-30T08:30:00.000Z"},{"date":"1962","value":"57920","label":"1962","year":"1962","month":"","quarter":"","sourceDataset":"UKEA","updateDate":"2016-06-30T08:30:00.000Z"},{"date":"1963","value":"60102","label":"1963","year":"1963","month":"","quarter":"","sourceDataset":"UKEA","updateDate":"2016-06-30T08:30:00.000Z"},{"date":"1964","value":"66601","label":"1964","year":"1964","month":"","quarter":"","sourceDataset":"UKEA","updateDate":"2016-06-30T08:30:00.000Z"},{"date":"1965","value":"67238","label":"1965","year":"1965","month":"","quarter":"","sourceDataset":"UKEA","updateDate":"2016-06-30T08:30:00.000Z"},{"date":"1966","value":"68949","label":"1966","year":"1966","month":"","quarter":"","sourceDataset":"UKEA","updateDate":"2016-06-30T08:30:00.000Z"},{"date":"1967","value":"73901","label":"1967","year":"1967","month":"","quarter":"","sourceDataset":"UKEA","updateDate":"2016-06-30T08:30:00.000Z"},{"date":"1968","value":"79566","label":"1968","year":"1968","month":"","quarter":"","sourceDataset":"UKEA","updateDate":"2016-06-30T08:30:00.000Z"},{"date":"1969","value":"82190","label":"1969","year":"1969","month":"","quarter":"","sourceDataset":"UKEA","updateDate":"2016-06-30T08:30:00.000Z"},{"date":"1970","value":"86207","label":"1970","year":"1970","month":"","quarter":"","sourceDataset":"UKEA","updateDate":"2016-06-30T08:30:00.000Z"},{"date":"1971","value":"90841","label":"1971","year":"1971","month":"","quarter":"","sourceDataset":"UKEA","updateDate":"2016-06-30T08:30:00.000Z"},{"date":"1972","value":"99808","label":"1972","year":"1972","month":"","quarter":"","sourceDataset":"UKEA","updateDate":"2016-06-30T08:30:00.000Z"},{"date":"1973","value":"110889","label":"1973","year":"1973","month":"","quarter":"","sourceDataset":"UKEA","updateDate":"2016-06-30T08:30:00.000Z"},{"date":"1974","value":"112186","label":"1974","year":"1974","month":"","quarter":"","sourceDataset":"UKEA","updateDate":"2016-06-30T08:30:00.000Z"},{"date":"1975","value":"104921","label":"1975","year":"1975","month":"","quarter":"","sourceDataset":"UKEA","updateDate":"2016-06-30T08:30:00.000Z"},{"date":"1976","value":"110353","label":"1976","year":"1976","month":"","quarter":"","sourceDataset":"UKEA","updateDate":"2016-06-30T08:30:00.000Z"},{"date":"1977","value":"112496","label":"1977","year":"1977","month":"","quarter":"","sourceDataset":"UKEA","updateDate":"2016-06-30T08:30:00.000Z"},{"date":"1978","value":"116735","label":"1978","year":"1978","month":"","quarter":"","sourceDataset":"UKEA","updateDate":"2016-06-30T08:30:00.000Z"},{"date":"1979","value":"127982","label":"1979","year":"1979","month":"","quarter":"","sourceDataset":"UKEA","updateDate":"2016-06-30T08:30:00.000Z"},{"date":"1980","value":"123677","label":"1980","year":"1980","month":"","quarter":"","sourceDataset":"UKEA","updateDate":"2016-06-30T08:30:00.000Z"},{"date":"1981","value":"120344","label":"1981","year":"1981","month":"","quarter":"","sourceDataset":"UKEA","updateDate":"2016-06-30T08:30:00.000Z"},{"date":"1982","value":"126272","label":"1982","year":"1982","month":"","quarter":"","sourceDataset":"UKEA","updateDate":"2016-06-30T08:30:00.000Z"},{"date":"1983","value":"134548","label":"1983","year":"1983","month":"","quarter":"","sourceDataset":"UKEA","updateDate":"2016-06-30T08:30:00.000Z"},{"date":"1984","value":"147783","label":"1984","year":"1984","month":"","quarter":"","sourceDataset":"UKEA","updateDate":"2016-06-30T08:30:00.000Z"},{"date":"1985","value":"151526","label":"1985","year":"1985","month":"","quarter":"","sourceDataset":"UKEA","updateDate":"2016-06-30T08:30:00.000Z"},{"date":"1986","value":"162024","label":"1986","year":"1986","month":"","quarter":"","sourceDataset":"UKEA","updateDate":"2016-06-30T08:30:00.000Z"},{"date":"1987","value":"174946","label":"1987","year":"1987","month":"","quarter":"","sourceDataset":"UKEA","updateDate":"2016-06-30T08:30:00.000Z"},{"date":"1988","value":"197356","label":"1988","year":"1988","month":"","quarter":"","sourceDataset":"UKEA","updateDate":"2016-06-30T08:30:00.000Z"},{"date":"1989","value":"212061","label":"1989","year":"1989","month":"","quarter":"","sourceDataset":"UKEA","updateDate":"2016-06-30T08:30:00.000Z"},{"date":"1990","value":"213365","label":"1990","year":"1990","month":"","quarter":"","sourceDataset":"UKEA","updateDate":"2016-06-30T08:30:00.000Z"},{"date":"1991","value":"204188","label":"1991","year":"1991","month":"","quarter":"","sourceDataset":"UKEA","updateDate":"2016-06-30T08:30:00.000Z"},{"date":"1992","value":"218078","label":"1992","year":"1992","month":"","quarter":"","sourceDataset":"UKEA","updateDate":"2016-06-30T08:30:00.000Z"},{"date":"1993","value":"225351","label":"1993","year":"1993","month":"","quarter":"","sourceDataset":"UKEA","updateDate":"2016-06-30T08:30:00.000Z"},{"date":"1994","value":"238823","label":"1994","year":"1994","month":"","quarter":"","sourceDataset":"UKEA","updateDate":"2016-06-30T08:30:00.000Z"},{"date":"1995","value":"252099","label":"1995","year":"1995","month":"","quarter":"","sourceDataset":"UKEA","updateDate":"2016-06-30T08:30:00.000Z"},{"date":"1996","value":"276104","label":"1996","year":"1996","month":"","quarter":"","sourceDataset":"UKEA","updateDate":"2016-06-30T08:30:00.000Z"},{"date":"1997","value":"298974","label":"1997","year":"1997","month":"","quarter":"","sourceDataset":"UKEA","updateDate":"2016-06-30T08:30:00.000Z"},{"date":"1998","value":"326343","label":"1998","year":"1998","month":"","quarter":"","sourceDataset":"UKEA","updateDate":"2016-06-30T08:30:00.000Z"},{"date":"1999","value":"350342","label":"1999","year":"1999","month":"","quarter":"","sourceDataset":"UKEA","updateDate":"2016-06-30T08:30:00.000Z"},{"date":"2000","value":"383881","label":"2000","year":"2000","month":"","quarter":"","sourceDataset":"UKEA","updateDate":"2016-06-30T08:30:00.000Z"},{"date":"2001","value":"402057","label":"2001","year":"2001","month":"","quarter":"","sourceDataset":"UKEA","updateDate":"2016-06-30T08:30:00.000Z"},{"date":"2002","value":"424230","label":"2002","year":"2002","month":"","quarter":"","sourceDataset":"UKEA","updateDate":"2016-06-30T08:30:00.000Z"},{"date":"2003","value":"435813","label":"2003","year":"2003","month":"","quarter":"","sourceDataset":"UKEA","updateDate":"2016-06-30T08:30:00.000Z"},{"date":"2004","value":"464702","label":"2004","year":"2004","month":"","quarter":"","sourceDataset":"UKEA","updateDate":"2016-06-30T08:30:00.000Z"},{"date":"2005","value":"495255","label":"2005","year":"2005","month":"","quarter":"","sourceDataset":"UKEA","updateDate":"2016-06-30T08:30:00.000Z"},{"date":"2006","value":"545109","label":"2006","year":"2006","month":"","quarter":"","sourceDataset":"UKEA","updateDate":"2016-06-30T08:30:00.000Z"},{"date":"2007","value":"538597","label":"2007","year":"2007","month":"","quarter":"","sourceDataset":"UKEA","updateDate":"2016-06-30T08:30:00.000Z"},{"date":"2008","value":"528606","label":"2008","year":"2008","month":"","quarter":"","sourceDataset":"UKEA","updateDate":"2016-06-30T08:30:00.000Z"},{"date":"2009","value":"480099","label":"2009","year":"2009","month":"","quarter":"","sourceDataset":"UKEA","updateDate":"2016-06-30T08:30:00.000Z"},{"date":"2010","value":"519251","label":"2010","year":"2010","month":"","quarter":"","sourceDataset":"UKEA","updateDate":"2016-06-30T08:30:00.000Z"},{"date":"2011","value":"523536","label":"2011","year":"2011","month":"","quarter":"","sourceDataset":"UKEA","updateDate":"2016-06-30T08:30:00.000Z"},{"date":"2012","value":"538482","label":"2012","year":"2012","month":"","quarter":"","sourceDataset":"UKEA","updateDate":"2016-06-30T08:30:00.000Z"},{"date":"2013","value":"556880","label":"2013","year":"2013","month":"","quarter":"","sourceDataset":"UKEA","updateDate":"2016-06-30T08:30:00.000Z"},{"date":"2014","value":"570989","label":"2014","year":"2014","month":"","quarter":"","sourceDataset":"UKEA","updateDate":"2016-06-30T08:30:00.000Z"},{"date":"2015","value":"601740","label":"2015","year":"2015","month":"","quarter":"","sourceDataset":"UKEA","updateDate":"2016-09-29T23:00:00.000Z"}],"quarters":[{"date":"1955 Q1","value":"11743","label":"1955 Q1","year":"1955","month":"","quarter":"Q1","sourceDataset":"UKEA","updateDate":"2016-06-30T08:30:00.000Z"},{"date":"1955 Q2","value":"10812","label":"1955 Q2","year":"1955","month":"","quarter":"Q2","sourceDataset":"UKEA","updateDate":"2016-06-30T08:30:00.000Z"},{"date":"1955 Q3","value":"11659","label":"1955 Q3","year":"1955","month":"","quarter":"Q3","sourceDataset":"UKEA","updateDate":"2016-06-30T08:30:00.000Z"},{"date":"1955 Q4","value":"11710","label":"1955 Q4","year":"1955","month":"","quarter":"Q4","sourceDataset":"UKEA","updateDate":"2016-06-30T08:30:00.000Z"},{"date":"1956 Q1","value":"11854","label":"1956 Q1","year":"1956","month":"","quarter":"Q1","sourceDataset":"UKEA","updateDate":"2016-06-30T08:30:00.000Z"},{"date":"1956 Q2","value":"11637","label":"1956 Q2","year":"1956","month":"","quarter":"Q2","sourceDataset":"UKEA","updateDate":"2016-06-30T08:30:00.000Z"},{"date":"1956 Q3","value":"11215","label":"1956 Q3","year":"1956","month":"","quarter":"Q3","sourceDataset":"UKEA","updateDate":"2016-06-30T08:30:00.000Z"},{"date":"1956 Q4","value":"11383","label":"1956 Q4","year":"1956","month":"","quarter":"Q4","sourceDataset":"UKEA","updateDate":"2016-06-30T08:30:00.000Z"},{"date":"1957 Q1","value":"12109","label":"1957 Q1","year":"1957","month":"","quarter":"Q1","sourceDataset":"UKEA","updateDate":"2016-06-30T08:30:00.000Z"},{"date":"1957 Q2","value":"11622","label":"1957 Q2","year":"1957","month":"","quarter":"Q2","sourceDataset":"UKEA","updateDate":"2016-06-30T08:30:00.000Z"},{"date":"1957 Q3","value":"11837","label":"1957 Q3","year":"1957","month":"","quarter":"Q3","sourceDataset":"UKEA","updateDate":"2016-06-30T08:30:00.000Z"},{"date":"1957 Q4","value":"11694","label":"1957 Q4","year":"1957","month":"","quarter":"Q4","sourceDataset":"UKEA","updateDate":"2016-06-30T08:30:00.000Z"},{"date":"1958 Q1","value":"11763","label":"1958 Q1","year":"1958","month":"","quarter":"Q1","sourceDataset":"UKEA","updateDate":"2016-06-30T08:30:00.000Z"},{"date":"1958 Q2","value":"11622","label":"1958 Q2","year":"1958","month":"","quarter":"Q2","sourceDataset":"UKEA","updateDate":"2016-06-30T08:30:00.000Z"},{"date":"1958 Q3","value":"11909","label":"1958 Q3","year":"1958","month":"","quarter":"Q3","sourceDataset":"UKEA","updateDate":"2016-06-30T08:30:00.000Z"},{"date":"1958 Q4","value":"12507","label":"1958 Q4","year":"1958","month":"","quarter":"Q4","sourceDataset":"UKEA","updateDate":"2016-06-30T08:30:00.000Z"},{"date":"1959 Q1","value":"12170","label":"1959 Q1","year":"1959","month":"","quarter":"Q1","sourceDataset":"UKEA","updateDate":"2016-06-30T08:30:00.000Z"},{"date":"1959 Q2","value":"12894","label":"1959 Q2","year":"1959","month":"","quarter":"Q2","sourceDataset":"UKEA","updateDate":"2016-06-30T08:30:00.000Z"},{"date":"1959 Q3","value":"12483","label":"1959 Q3","year":"1959","month":"","quarter":"Q3","sourceDataset":"UKEA","updateDate":"2016-06-30T08:30:00.000Z"},{"date":"1959 Q4","value":"13427","label":"1959 Q4","year":"1959","month":"","quarter":"Q4","sourceDataset":"UKEA","updateDate":"2016-06-30T08:30:00.000Z"},{"date":"1960 Q1","value":"14162","label":"1960 Q1","year":"1960","month":"","quarter":"Q1","sourceDataset":"UKEA","updateDate":"2016-06-30T08:30:00.000Z"},{"date":"1960 Q2","value":"14413","label":"1960 Q2","year":"1960","month":"","quarter":"Q2","sourceDataset":"UKEA","updateDate":"2016-06-30T08:30:00.000Z"},{"date":"1960 Q3","value":"14012","label":"1960 Q3","year":"1960","month":"","quarter":"Q3","sourceDataset":"UKEA","updateDate":"2016-06-30T08:30:00.000Z"},{"date":"1960 Q4","value":"14516","label":"1960 Q4","year":"1960","month":"","quarter":"Q4","sourceDataset":"UKEA","updateDate":"2016-06-30T08:30:00.000Z"},{"date":"1961 Q1","value":"14763","label":"1961 Q1","year":"1961","month":"","quarter":"Q1","sourceDataset":"UKEA","updateDate":"2016-06-30T08:30:00.000Z"},{"date":"1961 Q2","value":"14359","label":"1961 Q2","year":"1961","month":"","quarter":"Q2","sourceDataset":"UKEA","updateDate":"2016-06-30T08:30:00.000Z"},{"date":"1961 Q3","value":"13675","label":"1961 Q3","year":"1961","month":"","quarter":"Q3","sourceDataset":"UKEA","updateDate":"2016-06-30T08:30:00.000Z"},{"date":"1961 Q4","value":"13912","label":"1961 Q4","year":"1961","month":"","quarter":"Q4","sourceDataset":"UKEA","updateDate":"2016-06-30T08:30:00.000Z"},{"date":"1962 Q1","value":"14605","label":"1962 Q1","year":"1962","month":"","quarter":"Q1","sourceDataset":"UKEA","updateDate":"2016-06-30T08:30:00.000Z"},{"date":"1962 Q2","value":"14492","label":"1962 Q2","year":"1962","month":"","quarter":"Q2","sourceDataset":"UKEA","updateDate":"2016-06-30T08:30:00.000Z"},{"date":"1962 Q3","value":"14183","label":"1962 Q3","year":"1962","month":"","quarter":"Q3","sourceDataset":"UKEA","updateDate":"2016-06-30T08:30:00.000Z"},{"date":"1962 Q4","value":"14640","label":"1962 Q4","year":"1962","month":"","quarter":"Q4","sourceDataset":"UKEA","updateDate":"2016-06-30T08:30:00.000Z"},{"date":"1963 Q1","value":"14423","label":"1963 Q1","year":"1963","month":"","quarter":"Q1","sourceDataset":"UKEA","updateDate":"2016-06-30T08:30:00.000Z"},{"date":"1963 Q2","value":"14952","label":"1963 Q2","year":"1963","month":"","quarter":"Q2","sourceDataset":"UKEA","updateDate":"2016-06-30T08:30:00.000Z"},{"date":"1963 Q3","value":"15075","label":"1963 Q3","year":"1963","month":"","quarter":"Q3","sourceDataset":"UKEA","updateDate":"2016-06-30T08:30:00.000Z"},{"date":"1963 Q4","value":"15652","label":"1963 Q4","year":"1963","month":"","quarter":"Q4","sourceDataset":"UKEA","updateDate":"2016-06-30T08:30:00.000Z"},{"date":"1964 Q1","value":"16470","label":"1964 Q1","year":"1964","month":"","quarter":"Q1","sourceDataset":"UKEA","updateDate":"2016-06-30T08:30:00.000Z"},{"date":"1964 Q2","value":"16676","label":"1964 Q2","year":"1964","month":"","quarter":"Q2","sourceDataset":"UKEA","updateDate":"2016-06-30T08:30:00.000Z"},{"date":"1964 Q3","value":"16425","label":"1964 Q3","year":"1964","month":"","quarter":"Q3","sourceDataset":"UKEA","updateDate":"2016-06-30T08:30:00.000Z"},{"date":"1964 Q4","value":"17030","label":"1964 Q4","year":"1964","month":"","quarter":"Q4","sourceDataset":"UKEA","updateDate":"2016-06-30T08:30:00.000Z"},{"date":"1965 Q1","value":"15819","label":"1965 Q1","year":"1965","month":"","quarter":"Q1","sourceDataset":"UKEA","updateDate":"2016-06-30T08:30:00.000Z"},{"date":"1965 Q2","value":"16921","label":"1965 Q2","year":"1965","month":"","quarter":"Q2","sourceDataset":"UKEA","updateDate":"2016-06-30T08:30:00.000Z"},{"date":"1965 Q3","value":"17598","label":"1965 Q3","year":"1965","month":"","quarter":"Q3","sourceDataset":"UKEA","updateDate":"2016-06-30T08:30:00.000Z"},{"date":"1965 Q4","value":"16900","label":"1965 Q4","year":"1965","month":"","quarter":"Q4","sourceDataset":"UKEA","updateDate":"2016-06-30T08:30:00.000Z"},{"date":"1966 Q1","value":"17409","label":"1966 Q1","year":"1966","month":"","quarter":"Q1","sourceDataset":"UKEA","updateDate":"2016-06-30T08:30:00.000Z"},{"date":"1966 Q2","value":"17258","label":"1966 Q2","year":"1966","month":"","quarter":"Q2","sourceDataset":"UKEA","updateDate":"2016-06-30T08:30:00.000Z"},{"date":"1966 Q3","value":"18191","label":"1966 Q3","year":"1966","month":"","quarter":"Q3","sourceDataset":"UKEA","updateDate":"2016-06-30T08:30:00.000Z"},{"date":"1966 Q4","value":"16091","label":"1966 Q4","year":"1966","month":"","quarter":"Q4","sourceDataset":"UKEA","updateDate":"2016-06-30T08:30:00.000Z"},{"date":"1967 Q1","value":"17752","label":"1967 Q1","year":"1967","month":"","quarter":"Q1","sourceDataset":"UKEA","updateDate":"2016-06-30T08:30:00.000Z"},{"date":"1967 Q2","value":"18636","label":"1967 Q2","year":"1967","month":"","quarter":"Q2","sourceDataset":"UKEA","updateDate":"2016-06-30T08:30:00.000Z"},{"date":"1967 Q3","value":"18611","label":"1967 Q3","year":"1967","month":"","quarter":"Q3","sourceDataset":"UKEA","updateDate":"2016-06-30T08:30:00.000Z"},{"date":"1967 Q4","value":"18902","label":"1967 Q4","year":"1967","month":"","quarter":"Q4","sourceDataset":"UKEA","updateDate":"2016-06-30T08:30:00.000Z"},{"date":"1968 Q1","value":"20025","label":"1968 Q1","year":"1968","month":"","quarter":"Q1","sourceDataset":"UKEA","updateDate":"2016-06-30T08:30:00.000Z"},{"date":"1968 Q2","value":"19589","label":"1968 Q2","year":"1968","month":"","quarter":"Q2","sourceDataset":"UKEA","updateDate":"2016-06-30T08:30:00.000Z"},{"date":"1968 Q3","value":"20314","label":"1968 Q3","year":"1968","month":"","quarter":"Q3","sourceDataset":"UKEA","updateDate":"2016-06-30T08:30:00.000Z"},{"date":"1968 Q4","value":"19638","label":"1968 Q4","year":"1968","month":"","quarter":"Q4","sourceDataset":"UKEA","updateDate":"2016-06-30T08:30:00.000Z"},{"date":"1969 Q1","value":"20466","label":"1969 Q1","year":"1969","month":"","quarter":"Q1","sourceDataset":"UKEA","updateDate":"2016-06-30T08:30:00.000Z"},{"date":"1969 Q2","value":"20600","label":"1969 Q2","year":"1969","month":"","quarter":"Q2","sourceDataset":"UKEA","updateDate":"2016-06-30T08:30:00.000Z"},{"date":"1969 Q3","value":"20678","label":"1969 Q3","year":"1969","month":"","quarter":"Q3","sourceDataset":"UKEA","updateDate":"2016-06-30T08:30:00.000Z"},{"date":"1969 Q4","value":"20446","label":"1969 Q4","year":"1969","month":"","quarter":"Q4","sourceDataset":"UKEA","updateDate":"2016-06-30T08:30:00.000Z"},{"date":"1970 Q1","value":"20071","label":"1970 Q1","year":"1970","month":"","quarter":"Q1","sourceDataset":"UKEA","updateDate":"2016-06-30T08:30:00.000Z"},{"date":"1970 Q2","value":"22038","label":"1970 Q2","year":"1970","month":"","quarter":"Q2","sourceDataset":"UKEA","updateDate":"2016-06-30T08:30:00.000Z"},{"date":"1970 Q3","value":"21667","label":"1970 Q3","year":"1970","month":"","quarter":"Q3","sourceDataset":"UKEA","updateDate":"2016-06-30T08:30:00.000Z"},{"date":"1970 Q4","value":"22431","label":"1970 Q4","year":"1970","month":"","quarter":"Q4","sourceDataset":"UKEA","updateDate":"2016-06-30T08:30:00.000Z"},{"date":"1971 Q1","value":"22357","label":"1971 Q1","year":"1971","month":"","quarter":"Q1","sourceDataset":"UKEA","updateDate":"2016-06-30T08:30:00.000Z"},{"date":"1971 Q2","value":"22987","label":"1971 Q2","year":"1971","month":"","quarter":"Q2","sourceDataset":"UKEA","updateDate":"2016-06-30T08:30:00.000Z"},{"date":"1971 Q3","value":"22660","label":"1971 Q3","year":"1971","month":"","quarter":"Q3","sourceDataset":"UKEA","updateDate":"2016-06-30T08:30:00.000Z"},{"date":"1971 Q4","value":"22837","label":"1971 Q4","year":"1971","month":"","quarter":"Q4","sourceDataset":"UKEA","updateDate":"2016-06-30T08:30:00.000Z"},{"date":"1972 Q1","value":"24358","label":"1972 Q1","year":"1972","month":"","quarter":"Q1","sourceDataset":"UKEA","updateDate":"2016-06-30T08:30:00.000Z"},{"date":"1972 Q2","value":"24994","label":"1972 Q2","year":"1972","month":"","quarter":"Q2","sourceDataset":"UKEA","updateDate":"2016-06-30T08:30:00.000Z"},{"date":"1972 Q3","value":"23916","label":"1972 Q3","year":"1972","month":"","quarter":"Q3","sourceDataset":"UKEA","updateDate":"2016-06-30T08:30:00.000Z"},{"date":"1972 Q4","value":"26540","label":"1972 Q4","year":"1972","month":"","quarter":"Q4","sourceDataset":"UKEA","updateDate":"2016-06-30T08:30:00.000Z"},{"date":"1973 Q1","value":"27549","label":"1973 Q1","year":"1973","month":"","quarter":"Q1","sourceDataset":"UKEA","updateDate":"2016-06-30T08:30:00.000Z"},{"date":"1973 Q2","value":"27434","label":"1973 Q2","year":"1973","month":"","quarter":"Q2","sourceDataset":"UKEA","updateDate":"2016-06-30T08:30:00.000Z"},{"date":"1973 Q3","value":"27763","label":"1973 Q3","year":"1973","month":"","quarter":"Q3","sourceDataset":"UKEA","updateDate":"2016-06-30T08:30:00.000Z"},{"date":"1973 Q4","value":"28143","label":"1973 Q4","year":"1973","month":"","quarter":"Q4","sourceDataset":"UKEA","updateDate":"2016-06-30T08:30:00.000Z"},{"date":"1974 Q1","value":"27579","label":"1974 Q1","year":"1974","month":"","quarter":"Q1","sourceDataset":"UKEA","updateDate":"2016-06-30T08:30:00.000Z"},{"date":"1974 Q2","value":"28734","label":"1974 Q2","year":"1974","month":"","quarter":"Q2","sourceDataset":"UKEA","updateDate":"2016-06-30T08:30:00.000Z"},{"date":"1974 Q3","value":"28216","label":"1974 Q3","year":"1974","month":"","quarter":"Q3","sourceDataset":"UKEA","updateDate":"2016-06-30T08:30:00.000Z"},{"date":"1974 Q4","value":"27657","label":"1974 Q4","year":"1974","month":"","quarter":"Q4","sourceDataset":"UKEA","updateDate":"2016-06-30T08:30:00.000Z"},{"date":"1975 Q1","value":"25891","label":"1975 Q1","year":"1975","month":"","quarter":"Q1","sourceDataset":"UKEA","updateDate":"2016-06-30T08:30:00.000Z"},{"date":"1975 Q2","value":"26231","label":"1975 Q2","year":"1975","month":"","quarter":"Q2","sourceDataset":"UKEA","updateDate":"2016-06-30T08:30:00.000Z"},{"date":"1975 Q3","value":"26727","label":"1975 Q3","year":"1975","month":"","quarter":"Q3","sourceDataset":"UKEA","updateDate":"2016-06-30T08:30:00.000Z"},{"date":"1975 Q4","value":"26072","label":"1975 Q4","year":"1975","month":"","quarter":"Q4","sourceDataset":"UKEA","updateDate":"2016-06-30T08:30:00.000Z"},{"date":"1976 Q1","value":"25945","label":"1976 Q1","year":"1976","month":"","quarter":"Q1","sourceDataset":"UKEA","updateDate":"2016-06-30T08:30:00.000Z"},{"date":"1976 Q2","value":"28230","label":"1976 Q2","year":"1976","month":"","quarter":"Q2","sourceDataset":"UKEA","updateDate":"2016-06-30T08:30:00.000Z"},{"date":"1976 Q3","value":"28083","label":"1976 Q3","year":"1976","month":"","quarter":"Q3","sourceDataset":"UKEA","updateDate":"2016-06-30T08:30:00.000Z"},{"date":"1976 Q4","value":"28095","label":"1976 Q4","year":"1976","month":"","quarter":"Q4","sourceDataset":"UKEA","updateDate":"2016-06-30T08:30:00.000Z"},{"date":"1977 Q1","value":"28003","label":"1977 Q1","year":"1977","month":"","quarter":"Q1","sourceDataset":"UKEA","updateDate":"2016-06-30T08:30:00.000Z"},{"date":"1977 Q2","value":"29064","label":"1977 Q2","year":"1977","month":"","quarter":"Q2","sourceDataset":"UKEA","updateDate":"2016-06-30T08:30:00.000Z"},{"date":"1977 Q3","value":"28080","label":"1977 Q3","year":"1977","month":"","quarter":"Q3","sourceDataset":"UKEA","updateDate":"2016-06-30T08:30:00.000Z"},{"date":"1977 Q4","value":"27349","label":"1977 Q4","year":"1977","month":"","quarter":"Q4","sourceDataset":"UKEA","updateDate":"2016-06-30T08:30:00.000Z"},{"date":"1978 Q1","value":"29156","label":"1978 Q1","year":"1978","month":"","quarter":"Q1","sourceDataset":"UKEA","updateDate":"2016-06-30T08:30:00.000Z"},{"date":"1978 Q2","value":"30683","label":"1978 Q2","year":"1978","month":"","quarter":"Q2","sourceDataset":"UKEA","updateDate":"2016-06-30T08:30:00.000Z"},{"date":"1978 Q3","value":"29329","label":"1978 Q3","year":"1978","month":"","quarter":"Q3","sourceDataset":"UKEA","updateDate":"2016-06-30T08:30:00.000Z"},{"date":"1978 Q4","value":"27567","label":"1978 Q4","year":"1978","month":"","quarter":"Q4","sourceDataset":"UKEA","updateDate":"2016-06-30T08:30:00.000Z"},{"date":"1979 Q1","value":"29923","label":"1979 Q1","year":"1979","month":"","quarter":"Q1","sourceDataset":"UKEA","updateDate":"2016-06-30T08:30:00.000Z"},{"date":"1979 Q2","value":"32655","label":"1979 Q2","year":"1979","month":"","quarter":"Q2","sourceDataset":"UKEA","updateDate":"2016-06-30T08:30:00.000Z"},{"date":"1979 Q3","value":"32757","label":"1979 Q3","year":"1979","month":"","quarter":"Q3","sourceDataset":"UKEA","updateDate":"2016-06-30T08:30:00.000Z"},{"date":"1979 Q4","value":"32647","label":"1979 Q4","year":"1979","month":"","quarter":"Q4","sourceDataset":"UKEA","updateDate":"2016-06-30T08:30:00.000Z"},{"date":"1980 Q1","value":"33217","label":"1980 Q1","year":"1980","month":"","quarter":"Q1","sourceDataset":"UKEA","updateDate":"2016-06-30T08:30:00.000Z"},{"date":"1980 Q2","value":"32381","label":"1980 Q2","year":"1980","month":"","quarter":"Q2","sourceDataset":"UKEA","updateDate":"2016-06-30T08:30:00.000Z"},{"date":"1980 Q3","value":"29915","label":"1980 Q3","year":"1980","month":"","quarter":"Q3","sourceDataset":"UKEA","updateDate":"2016-06-30T08:30:00.000Z"},{"date":"1980 Q4","value":"28164","label":"1980 Q4","year":"1980","month":"","quarter":"Q4","sourceDataset":"UKEA","updateDate":"2016-06-30T08:30:00.000Z"},{"date":"1981 Q1","value":"27076","label":"1981 Q1","year":"1981","month":"","quarter":"Q1","sourceDataset":"UKEA","updateDate":"2016-06-30T08:30:00.000Z"},{"date":"1981 Q2","value":"29580","label":"1981 Q2","year":"1981","month":"","quarter":"Q2","sourceDataset":"UKEA","updateDate":"2016-06-30T08:30:00.000Z"},{"date":"1981 Q3","value":"32626","label":"1981 Q3","year":"1981","month":"","quarter":"Q3","sourceDataset":"UKEA","updateDate":"2016-06-30T08:30:00.000Z"},{"date":"1981 Q4","value":"31062","label":"1981 Q4","year":"1981","month":"","quarter":"Q4","sourceDataset":"UKEA","updateDate":"2016-06-30T08:30:00.000Z"},{"date":"1982 Q1","value":"30685","label":"1982 Q1","year":"1982","month":"","quarter":"Q1","sourceDataset":"UKEA","updateDate":"2016-06-30T08:30:00.000Z"},{"date":"1982 Q2","value":"32867","label":"1982 Q2","year":"1982","month":"","quarter":"Q2","sourceDataset":"UKEA","updateDate":"2016-06-30T08:30:00.000Z"},{"date":"1982 Q3","value":"32025","label":"1982 Q3","year":"1982","month":"","quarter":"Q3","sourceDataset":"UKEA","updateDate":"2016-06-30T08:30:00.000Z"},{"date":"1982 Q4","value":"30695","label":"1982 Q4","year":"1982","month":"","quarter":"Q4","sourceDataset":"UKEA","updateDate":"2016-06-30T08:30:00.000Z"},{"date":"1983 Q1","value":"32149","label":"1983 Q1","year":"1983","month":"","quarter":"Q1","sourceDataset":"UKEA","updateDate":"2016-06-30T08:30:00.000Z"},{"date":"1983 Q2","value":"33926","label":"1983 Q2","year":"1983","month":"","quarter":"Q2","sourceDataset":"UKEA","updateDate":"2016-06-30T08:30:00.000Z"},{"date":"1983 Q3","value":"34355","label":"1983 Q3","year":"1983","month":"","quarter":"Q3","sourceDataset":"UKEA","updateDate":"2016-06-30T08:30:00.000Z"},{"date":"1983 Q4","value":"34118","label":"1983 Q4","year":"1983","month":"","quarter":"Q4","sourceDataset":"UKEA","updateDate":"2016-06-30T08:30:00.000Z"},{"date":"1984 Q1","value":"35054","label":"1984 Q1","year":"1984","month":"","quarter":"Q1","sourceDataset":"UKEA","updateDate":"2016-06-30T08:30:00.000Z"},{"date":"1984 Q2","value":"37162","label":"1984 Q2","year":"1984","month":"","quarter":"Q2","sourceDataset":"UKEA","updateDate":"2016-06-30T08:30:00.000Z"},{"date":"1984 Q3","value":"37229","label":"1984 Q3","year":"1984","month":"","quarter":"Q3","sourceDataset":"UKEA","updateDate":"2016-06-30T08:30:00.000Z"},{"date":"1984 Q4","value":"38338","label":"1984 Q4","year":"1984","month":"","quarter":"Q4","sourceDataset":"UKEA","updateDate":"2016-06-30T08:30:00.000Z"},{"date":"1985 Q1","value":"37928","label":"1985 Q1","year":"1985","month":"","quarter":"Q1","sourceDataset":"UKEA","updateDate":"2016-06-30T08:30:00.000Z"},{"date":"1985 Q2","value":"38053","label":"1985 Q2","year":"1985","month":"","quarter":"Q2","sourceDataset":"UKEA","updateDate":"2016-06-30T08:30:00.000Z"},{"date":"1985 Q3","value":"37531","label":"1985 Q3","year":"1985","month":"","quarter":"Q3","sourceDataset":"UKEA","updateDate":"2016-06-30T08:30:00.000Z"},{"date":"1985 Q4","value":"38014","label":"1985 Q4","year":"1985","month":"","quarter":"Q4","sourceDataset":"UKEA","updateDate":"2016-06-30T08:30:00.000Z"},{"date":"1986 Q1","value":"37405","label":"1986 Q1","year":"1986","month":"","quarter":"Q1","sourceDataset":"UKEA","updateDate":"2016-06-30T08:30:00.000Z"},{"date":"1986 Q2","value":"41398","label":"1986 Q2","year":"1986","month":"","quarter":"Q2","sourceDataset":"UKEA","updateDate":"2016-06-30T08:30:00.000Z"},{"date":"1986 Q3","value":"42017","label":"1986 Q3","year":"1986","month":"","quarter":"Q3","sourceDataset":"UKEA","updateDate":"2016-06-30T08:30:00.000Z"},{"date":"1986 Q4","value":"41204","label":"1986 Q4","year":"1986","month":"","quarter":"Q4","sourceDataset":"UKEA","updateDate":"2016-06-30T08:30:00.000Z"},{"date":"1987 Q1","value":"39558","label":"1987 Q1","year":"1987","month":"","quarter":"Q1","sourceDataset":"UKEA","updateDate":"2016-06-30T08:30:00.000Z"},{"date":"1987 Q2","value":"43303","label":"1987 Q2","year":"1987","month":"","quarter":"Q2","sourceDataset":"UKEA","updateDate":"2016-06-30T08:30:00.000Z"},{"date":"1987 Q3","value":"46513","label":"1987 Q3","year":"1987","month":"","quarter":"Q3","sourceDataset":"UKEA","updateDate":"2016-06-30T08:30:00.000Z"},{"date":"1987 Q4","value":"45572","label":"1987 Q4","year":"1987","month":"","quarter":"Q4","sourceDataset":"UKEA","updateDate":"2016-06-30T08:30:00.000Z"},{"date":"1988 Q1","value":"45039","label":"1988 Q1","year":"1988","month":"","quarter":"Q1","sourceDataset":"UKEA","updateDate":"2016-06-30T08:30:00.000Z"},{"date":"1988 Q2","value":"49301","label":"1988 Q2","year":"1988","month":"","quarter":"Q2","sourceDataset":"UKEA","updateDate":"2016-06-30T08:30:00.000Z"},{"date":"1988 Q3","value":"51678","label":"1988 Q3","year":"1988","month":"","quarter":"Q3","sourceDataset":"UKEA","updateDate":"2016-06-30T08:30:00.000Z"},{"date":"1988 Q4","value":"51338","label":"1988 Q4","year":"1988","month":"","quarter":"Q4","sourceDataset":"UKEA","updateDate":"2016-06-30T08:30:00.000Z"},{"date":"1989 Q1","value":"51156","label":"1989 Q1","year":"1989","month":"","quarter":"Q1","sourceDataset":"UKEA","updateDate":"2016-06-30T08:30:00.000Z"},{"date":"1989 Q2","value":"54140","label":"1989 Q2","year":"1989","month":"","quarter":"Q2","sourceDataset":"UKEA","updateDate":"2016-06-30T08:30:00.000Z"},{"date":"1989 Q3","value":"55025","label":"1989 Q3","year":"1989","month":"","quarter":"Q3","sourceDataset":"UKEA","updateDate":"2016-06-30T08:30:00.000Z"},{"date":"1989 Q4","value":"51740","label":"1989 Q4","year":"1989","month":"","quarter":"Q4","sourceDataset":"UKEA","updateDate":"2016-06-30T08:30:00.000Z"},{"date":"1990 Q1","value":"52779","label":"1990 Q1","year":"1990","month":"","quarter":"Q1","sourceDataset":"UKEA","updateDate":"2016-06-30T08:30:00.000Z"},{"date":"1990 Q2","value":"54982","label":"1990 Q2","year":"1990","month":"","quarter":"Q2","sourceDataset":"UKEA","updateDate":"2016-06-30T08:30:00.000Z"},{"date":"1990 Q3","value":"54422","label":"1990 Q3","year":"1990","month":"","quarter":"Q3","sourceDataset":"UKEA","updateDate":"2016-06-30T08:30:00.000Z"},{"date":"1990 Q4","value":"51182","label":"1990 Q4","year":"1990","month":"","quarter":"Q4","sourceDataset":"UKEA","updateDate":"2016-06-30T08:30:00.000Z"},{"date":"1991 Q1","value":"48764","label":"1991 Q1","year":"1991","month":"","quarter":"Q1","sourceDataset":"UKEA","updateDate":"2016-06-30T08:30:00.000Z"},{"date":"1991 Q2","value":"52002","label":"1991 Q2","year":"1991","month":"","quarter":"Q2","sourceDataset":"UKEA","updateDate":"2016-06-30T08:30:00.000Z"},{"date":"1991 Q3","value":"52471","label":"1991 Q3","year":"1991","month":"","quarter":"Q3","sourceDataset":"UKEA","updateDate":"2016-06-30T08:30:00.000Z"},{"date":"1991 Q4","value":"50951","label":"1991 Q4","year":"1991","month":"","quarter":"Q4","sourceDataset":"UKEA","updateDate":"2016-06-30T08:30:00.000Z"},{"date":"1992 Q1","value":"51591","label":"1992 Q1","year":"1992","month":"","quarter":"Q1","sourceDataset":"UKEA","updateDate":"2016-06-30T08:30:00.000Z"},{"date":"1992 Q2","value":"55967","label":"1992 Q2","year":"1992","month":"","quarter":"Q2","sourceDataset":"UKEA","updateDate":"2016-06-30T08:30:00.000Z"},{"date":"1992 Q3","value":"56195","label":"1992 Q3","year":"1992","month":"","quarter":"Q3","sourceDataset":"UKEA","updateDate":"2016-06-30T08:30:00.000Z"},{"date":"1992 Q4","value":"54325","label":"1992 Q4","year":"1992","month":"","quarter":"Q4","sourceDataset":"UKEA","updateDate":"2016-06-30T08:30:00.000Z"},{"date":"1993 Q1","value":"54061","label":"1993 Q1","year":"1993","month":"","quarter":"Q1","sourceDataset":"UKEA","updateDate":"2016-06-30T08:30:00.000Z"},{"date":"1993 Q2","value":"56517","label":"1993 Q2","year":"1993","month":"","quarter":"Q2","sourceDataset":"UKEA","updateDate":"2016-06-30T08:30:00.000Z"},{"date":"1993 Q3","value":"58167","label":"1993 Q3","year":"1993","month":"","quarter":"Q3","sourceDataset":"UKEA","updateDate":"2016-06-30T08:30:00.000Z"},{"date":"1993 Q4","value":"56606","label":"1993 Q4","year":"1993","month":"","quarter":"Q4","sourceDataset":"UKEA","updateDate":"2016-06-30T08:30:00.000Z"},{"date":"1994 Q1","value":"57115","label":"1994 Q1","year":"1994","month":"","quarter":"Q1","sourceDataset":"UKEA","updateDate":"2016-06-30T08:30:00.000Z"},{"date":"1994 Q2","value":"60685","label":"1994 Q2","year":"1994","month":"","quarter":"Q2","sourceDataset":"UKEA","updateDate":"2016-06-30T08:30:00.000Z"},{"date":"1994 Q3","value":"60324","label":"1994 Q3","year":"1994","month":"","quarter":"Q3","sourceDataset":"UKEA","updateDate":"2016-06-30T08:30:00.000Z"},{"date":"1994 Q4","value":"60699","label":"1994 Q4","year":"1994","month":"","quarter":"Q4","sourceDataset":"UKEA","updateDate":"2016-06-30T08:30:00.000Z"},{"date":"1995 Q1","value":"58762","label":"1995 Q1","year":"1995","month":"","quarter":"Q1","sourceDataset":"UKEA","updateDate":"2016-06-30T08:30:00.000Z"},{"date":"1995 Q2","value":"64129","label":"1995 Q2","year":"1995","month":"","quarter":"Q2","sourceDataset":"UKEA","updateDate":"2016-06-30T08:30:00.000Z"},{"date":"1995 Q3","value":"65156","label":"1995 Q3","year":"1995","month":"","quarter":"Q3","sourceDataset":"UKEA","updateDate":"2016-06-30T08:30:00.000Z"},{"date":"1995 Q4","value":"64052","label":"1995 Q4","year":"1995","month":"","quarter":"Q4","sourceDataset":"UKEA","updateDate":"2016-06-30T08:30:00.000Z"},{"date":"1996 Q1","value":"65687","label":"1996 Q1","year":"1996","month":"","quarter":"Q1","sourceDataset":"UKEA","updateDate":"2016-06-30T08:30:00.000Z"},{"date":"1996 Q2","value":"69259","label":"1996 Q2","year":"1996","month":"","quarter":"Q2","sourceDataset":"UKEA","updateDate":"2016-06-30T08:30:00.000Z"},{"date":"1996 Q3","value":"70286","label":"1996 Q3","year":"1996","month":"","quarter":"Q3","sourceDataset":"UKEA","updateDate":"2016-06-30T08:30:00.000Z"},{"date":"1996 Q4","value":"70872","label":"1996 Q4","year":"1996","month":"","quarter":"Q4","sourceDataset":"UKEA","updateDate":"2016-06-30T08:30:00.000Z"},{"date":"1997 Q1","value":"68735","label":"1997 Q1","year":"1997","month":"","quarter":"Q1","sourceDataset":"UKEA","updateDate":"2016-06-30T08:30:00.000Z"},{"date":"1997 Q2","value":"75824","label":"1997 Q2","year":"1997","month":"","quarter":"Q2","sourceDataset":"UKEA","updateDate":"2016-06-30T08:30:00.000Z"},{"date":"1997 Q3","value":"76727","label":"1997 Q3","year":"1997","month":"","quarter":"Q3","sourceDataset":"UKEA","updateDate":"2016-06-30T08:30:00.000Z"},{"date":"1997 Q4","value":"77688","label":"1997 Q4","year":"1997","month":"","quarter":"Q4","sourceDataset":"UKEA","updateDate":"2016-06-30T08:30:00.000Z"},{"date":"1998 Q1","value":"76774","label":"1998 Q1","year":"1998","month":"","quarter":"Q1","sourceDataset":"UKEA","updateDate":"2016-06-30T08:30:00.000Z"},{"date":"1998 Q2","value":"82147","label":"1998 Q2","year":"1998","month":"","quarter":"Q2","sourceDataset":"UKEA","updateDate":"2016-06-30T08:30:00.000Z"},{"date":"1998 Q3","value":"84429","label":"1998 Q3","year":"1998","month":"","quarter":"Q3","sourceDataset":"UKEA","updateDate":"2016-06-30T08:30:00.000Z"},{"date":"1998 Q4","value":"82993","label":"1998 Q4","year":"1998","month":"","quarter":"Q4","sourceDataset":"UKEA","updateDate":"2016-06-30T08:30:00.000Z"},{"date":"1999 Q1","value":"81488","label":"1999 Q1","year":"1999","month":"","quarter":"Q1","sourceDataset":"UKEA","updateDate":"2016-06-30T08:30:00.000Z"},{"date":"1999 Q2","value":"85005","label":"1999 Q2","year":"1999","month":"","quarter":"Q2","sourceDataset":"UKEA","updateDate":"2016-06-30T08:30:00.000Z"},{"date":"1999 Q3","value":"92139","label":"1999 Q3","year":"1999","month":"","quarter":"Q3","sourceDataset":"UKEA","updateDate":"2016-06-30T08:30:00.000Z"},{"date":"1999 Q4","value":"91710","label":"1999 Q4","year":"1999","month":"","quarter":"Q4","sourceDataset":"UKEA","updateDate":"2016-06-30T08:30:00.000Z"},{"date":"2000 Q1","value":"89742","label":"2000 Q1","year":"2000","month":"","quarter":"Q1","sourceDataset":"UKEA","updateDate":"2016-06-30T08:30:00.000Z"},{"date":"2000 Q2","value":"94649","label":"2000 Q2","year":"2000","month":"","quarter":"Q2","sourceDataset":"UKEA","updateDate":"2016-06-30T08:30:00.000Z"},{"date":"2000 Q3","value":"99760","label":"2000 Q3","year":"2000","month":"","quarter":"Q3","sourceDataset":"UKEA","updateDate":"2016-06-30T08:30:00.000Z"},{"date":"2000 Q4","value":"99730","label":"2000 Q4","year":"2000","month":"","quarter":"Q4","sourceDataset":"UKEA","updateDate":"2016-06-30T08:30:00.000Z"},{"date":"2001 Q1","value":"98358","label":"2001 Q1","year":"2001","month":"","quarter":"Q1","sourceDataset":"UKEA","updateDate":"2016-06-30T08:30:00.000Z"},{"date":"2001 Q2","value":"101100","label":"2001 Q2","year":"2001","month":"","quarter":"Q2","sourceDataset":"UKEA","updateDate":"2016-06-30T08:30:00.000Z"},{"date":"2001 Q3","value":"102904","label":"2001 Q3","year":"2001","month":"","quarter":"Q3","sourceDataset":"UKEA","updateDate":"2016-06-30T08:30:00.000Z"},{"date":"2001 Q4","value":"99695","label":"2001 Q4","year":"2001","month":"","quarter":"Q4","sourceDataset":"UKEA","updateDate":"2016-06-30T08:30:00.000Z"},{"date":"2002 Q1","value":"99719","label":"2002 Q1","year":"2002","month":"","quarter":"Q1","sourceDataset":"UKEA","updateDate":"2016-06-30T08:30:00.000Z"},{"date":"2002 Q2","value":"108088","label":"2002 Q2","year":"2002","month":"","quarter":"Q2","sourceDataset":"UKEA","updateDate":"2016-06-30T08:30:00.000Z"},{"date":"2002 Q3","value":"110547","label":"2002 Q3","year":"2002","month":"","quarter":"Q3","sourceDataset":"UKEA","updateDate":"2016-06-30T08:30:00.000Z"},{"date":"2002 Q4","value":"105876","label":"2002 Q4","year":"2002","month":"","quarter":"Q4","sourceDataset":"UKEA","updateDate":"2016-06-30T08:30:00.000Z"},{"date":"2003 Q1","value":"105446","label":"2003 Q1","year":"2003","month":"","quarter":"Q1","sourceDataset":"UKEA","updateDate":"2016-06-30T08:30:00.000Z"},{"date":"2003 Q2","value":"107199","label":"2003 Q2","year":"2003","month":"","quarter":"Q2","sourceDataset":"UKEA","updateDate":"2016-06-30T08:30:00.000Z"},{"date":"2003 Q3","value":"111832","label":"2003 Q3","year":"2003","month":"","quarter":"Q3","sourceDataset":"UKEA","updateDate":"2016-06-30T08:30:00.000Z"},{"date":"2003 Q4","value":"111336","label":"2003 Q4","year":"2003","month":"","quarter":"Q4","sourceDataset":"UKEA","updateDate":"2016-06-30T08:30:00.000Z"},{"date":"2004 Q1","value":"109051","label":"2004 Q1","year":"2004","month":"","quarter":"Q1","sourceDataset":"UKEA","updateDate":"2016-06-30T08:30:00.000Z"},{"date":"2004 Q2","value":"114548","label":"2004 Q2","year":"2004","month":"","quarter":"Q2","sourceDataset":"UKEA","updateDate":"2016-06-30T08:30:00.000Z"},{"date":"2004 Q3","value":"121333","label":"2004 Q3","year":"2004","month":"","quarter":"Q3","sourceDataset":"UKEA","updateDate":"2016-06-30T08:30:00.000Z"},{"date":"2004 Q4","value":"119770","label":"2004 Q4","year":"2004","month":"","quarter":"Q4","sourceDataset":"UKEA","updateDate":"2016-06-30T08:30:00.000Z"},{"date":"2005 Q1","value":"114744","label":"2005 Q1","year":"2005","month":"","quarter":"Q1","sourceDataset":"UKEA","updateDate":"2016-06-30T08:30:00.000Z"},{"date":"2005 Q2","value":"123452","label":"2005 Q2","year":"2005","month":"","quarter":"Q2","sourceDataset":"UKEA","updateDate":"2016-06-30T08:30:00.000Z"},{"date":"2005 Q3","value":"129064","label":"2005 Q3","year":"2005","month":"","quarter":"Q3","sourceDataset":"UKEA","updateDate":"2016-06-30T08:30:00.000Z"},{"date":"2005 Q4","value":"127995","label":"2005 Q4","year":"2005","month":"","quarter":"Q4","sourceDataset":"UKEA","updateDate":"2016-06-30T08:30:00.000Z"},{"date":"2006 Q1","value":"138212","label":"2006 Q1","year":"2006","month":"","quarter":"Q1","sourceDataset":"UKEA","updateDate":"2016-06-30T08:30:00.000Z"},{"date":"2006 Q2","value":"144604","label":"2006 Q2","year":"2006","month":"","quarter":"Q2","sourceDataset":"UKEA","updateDate":"2016-06-30T08:30:00.000Z"},{"date":"2006 Q3","value":"133101","label":"2006 Q3","year":"2006","month":"","quarter":"Q3","sourceDataset":"UKEA","updateDate":"2016-06-30T08:30:00.000Z"},{"date":"2006 Q4","value":"129192","label":"2006 Q4","year":"2006","month":"","quarter":"Q4","sourceDataset":"UKEA","updateDate":"2016-06-30T08:30:00.000Z"},{"date":"2007 Q1","value":"129534","label":"2007 Q1","year":"2007","month":"","quarter":"Q1","sourceDataset":"UKEA","updateDate":"2016-06-30T08:30:00.000Z"},{"date":"2007 Q2","value":"132281","label":"2007 Q2","year":"2007","month":"","quarter":"Q2","sourceDataset":"UKEA","updateDate":"2016-06-30T08:30:00.000Z"},{"date":"2007 Q3","value":"140685","label":"2007 Q3","year":"2007","month":"","quarter":"Q3","sourceDataset":"UKEA","updateDate":"2016-06-30T08:30:00.000Z"},{"date":"2007 Q4","value":"136097","label":"2007 Q4","year":"2007","month":"","quarter":"Q4","sourceDataset":"UKEA","updateDate":"2016-06-30T08:30:00.000Z"},{"date":"2008 Q1","value":"131400","label":"2008 Q1","year":"2008","month":"","quarter":"Q1","sourceDataset":"UKEA","updateDate":"2016-06-30T08:30:00.000Z"},{"date":"2008 Q2","value":"135220","label":"2008 Q2","year":"2008","month":"","quarter":"Q2","sourceDataset":"UKEA","updateDate":"2016-06-30T08:30:00.000Z"},{"date":"2008 Q3","value":"135574","label":"2008 Q3","year":"2008","month":"","quarter":"Q3","sourceDataset":"UKEA","updateDate":"2016-06-30T08:30:00.000Z"},{"date":"2008 Q4","value":"126412","label":"2008 Q4","year":"2008","month":"","quarter":"Q4","sourceDataset":"UKEA","updateDate":"2016-06-30T08:30:00.000Z"},{"date":"2009 Q1","value":"116378","label":"2009 Q1","year":"2009","month":"","quarter":"Q1","sourceDataset":"UKEA","updateDate":"2016-06-30T08:30:00.000Z"},{"date":"2009 Q2","value":"117437","label":"2009 Q2","year":"2009","month":"","quarter":"Q2","sourceDataset":"UKEA","updateDate":"2016-06-30T08:30:00.000Z"},{"date":"2009 Q3","value":"122656","label":"2009 Q3","year":"2009","month":"","quarter":"Q3","sourceDataset":"UKEA","updateDate":"2016-06-30T08:30:00.000Z"},{"date":"2009 Q4","value":"123628","label":"2009 Q4","year":"2009","month":"","quarter":"Q4","sourceDataset":"UKEA","updateDate":"2016-06-30T08:30:00.000Z"},{"date":"2010 Q1","value":"121937","label":"2010 Q1","year":"2010","month":"","quarter":"Q1","sourceDataset":"UKEA","updateDate":"2016-06-30T08:30:00.000Z"},{"date":"2010 Q2","value":"127832","label":"2010 Q2","year":"2010","month":"","quarter":"Q2","sourceDataset":"UKEA","updateDate":"2016-06-30T08:30:00.000Z"},{"date":"2010 Q3","value":"136161","label":"2010 Q3","year":"2010","month":"","quarter":"Q3","sourceDataset":"UKEA","updateDate":"2016-06-30T08:30:00.000Z"},{"date":"2010 Q4","value":"133321","label":"2010 Q4","year":"2010","month":"","quarter":"Q4","sourceDataset":"UKEA","updateDate":"2016-06-30T08:30:00.000Z"},{"date":"2011 Q1","value":"126157","label":"2011 Q1","year":"2011","month":"","quarter":"Q1","sourceDataset":"UKEA","updateDate":"2016-06-30T08:30:00.000Z"},{"date":"2011 Q2","value":"128123","label":"2011 Q2","year":"2011","month":"","quarter":"Q2","sourceDataset":"UKEA","updateDate":"2016-06-30T08:30:00.000Z"},{"date":"2011 Q3","value":"134905","label":"2011 Q3","year":"2011","month":"","quarter":"Q3","sourceDataset":"UKEA","updateDate":"2016-06-30T08:30:00.000Z"},{"date":"2011 Q4","value":"134351","label":"2011 Q4","year":"2011","month":"","quarter":"Q4","sourceDataset":"UKEA","updateDate":"2016-06-30T08:30:00.000Z"},{"date":"2012 Q1","value":"131343","label":"2012 Q1","year":"2012","month":"","quarter":"Q1","sourceDataset":"UKEA","updateDate":"2016-06-30T08:30:00.000Z"},{"date":"2012 Q2","value":"134517","label":"2012 Q2","year":"2012","month":"","quarter":"Q2","sourceDataset":"UKEA","updateDate":"2016-06-30T08:30:00.000Z"},{"date":"2012 Q3","value":"137617","label":"2012 Q3","year":"2012","month":"","quarter":"Q3","sourceDataset":"UKEA","updateDate":"2016-06-30T08:30:00.000Z"},{"date":"2012 Q4","value":"135005","label":"2012 Q4","year":"2012","month":"","quarter":"Q4","sourceDataset":"UKEA","updateDate":"2016-06-30T08:30:00.000Z"},{"date":"2013 Q1","value":"130893","label":"2013 Q1","year":"2013","month":"","quarter":"Q1","sourceDataset":"UKEA","updateDate":"2016-06-30T08:30:00.000Z"},{"date":"2013 Q2","value":"139440","label":"2013 Q2","year":"2013","month":"","quarter":"Q2","sourceDataset":"UKEA","updateDate":"2016-06-30T08:30:00.000Z"},{"date":"2013 Q3","value":"142943","label":"2013 Q3","year":"2013","month":"","quarter":"Q3","sourceDataset":"UKEA","updateDate":"2016-06-30T08:30:00.000Z"},{"date":"2013 Q4","value":"143604","label":"2013 Q4","year":"2013","month":"","quarter":"Q4","sourceDataset":"UKEA","updateDate":"2016-06-30T08:30:00.000Z"},{"date":"2014 Q1","value":"139418","label":"2014 Q1","year":"2014","month":"","quarter":"Q1","sourceDataset":"UKEA","updateDate":"2016-06-30T08:30:00.000Z"},{"date":"2014 Q2","value":"139066","label":"2014 Q2","year":"2014","month":"","quarter":"Q2","sourceDataset":"UKEA","updateDate":"2016-06-30T08:30:00.000Z"},{"date":"2014 Q3","value":"145360","label":"2014 Q3","year":"2014","month":"","quarter":"Q3","sourceDataset":"UKEA","updateDate":"2016-06-30T08:30:00.000Z"},{"date":"2014 Q4","value":"147145","label":"2014 Q4","year":"2014","month":"","quarter":"Q4","sourceDataset":"UKEA","updateDate":"2016-06-30T08:30:00.000Z"},{"date":"2015 Q1","value":"148663","label":"2015 Q1","year":"2015","month":"","quarter":"Q1","sourceDataset":"UKEA","updateDate":"2016-09-29T23:00:00.000Z"},{"date":"2015 Q2","value":"147319","label":"2015 Q2","year":"2015","month":"","quarter":"Q2","sourceDataset":"UKEA","updateDate":"2016-09-29T23:00:00.000Z"},{"date":"2015 Q3","value":"152939","label":"2015 Q3","year":"2015","month":"","quarter":"Q3","sourceDataset":"UKEA","updateDate":"2016-09-29T23:00:00.000Z"},{"date":"2015 Q4","value":"152819","label":"2015 Q4","year":"2015","month":"","quarter":"Q4","sourceDataset":"UKEA","updateDate":"2016-09-29T23:00:00.000Z"},{"date":"2016 Q1","value":"150648","label":"2016 Q1","year":"2016","month":"","quarter":"Q1","sourceDataset":"UKEA","updateDate":"2016-09-29T23:00:00.000Z"},{"date":"2016 Q2","value":"156423","label":"2016 Q2","year":"2016","month":"","quarter":"Q2","sourceDataset":"UKEA","updateDate":"2016-09-29T23:00:00.000Z"}],"months":[],"sourceDatasets":[],"relatedDatasets":[{"uri":"/economy/grossdomesticproductgdp/datasets/unitedkingdomeconomicaccounts"}],"relatedDocuments":[],"versions":[{"uri":"/economy/grossdomesticproductgdp/timeseries/ktnb/ukea/previous/v1","updateDate":"2016-03-31T08:30:00.000Z","correctionNotice":"","label":"v1"},{"uri":"/economy/grossdomesticproductgdp/timeseries/ktnb/ukea/previous/v2","updateDate":"2016-06-30T08:30:00.000Z","correctionNotice":"","label":"v2"},{"uri":"/economy/grossdomesticproductgdp/timeseries/ktnb/ukea/previous/v3","updateDate":"2016-09-30T08:30:00.000Z","correctionNotice":"","label":"v3"}],"type":"timeseries","uri":"/economy/grossdomesticproductgdp/timeseries/ktnb/ukea","description":{"title":"Balance of Payments:Trade in Goods \u0026 Services: Total Imports: CVM NSA £m","contact":{"email":"sector.accounts@ons.gsi.gov.uk","name":"Michael Rizzo","telephone":"+44 (0)1633 456366"},"releaseDate":"2016-09-29T23:00:00.000Z","nextRelease":"23 December 2016","datasetId":"UKEA","datasetUri":"/economy/grossdomesticproductgdp/datasets/unitedkingdomeconomicaccounts","cdid":"KTNB","unit":"m","preUnit":"£","source":"","date":"2016 Q2","number":"156423","sampleSize":"0"}}